{
 "model": {
  "corney": {
   "-4": {
    "s_mps": 0.838,
    "n": 2
   },
   "-3": {
    "s_mps": 0.028,
    "n": 1
   },
   "-2": {
    "s_mps": 1.024,
    "n": 4
   },
   "-1": {
    "s_mps": 0.215,
    "n": 9
   },
   "+0": {
    "s_mps": -0.183,
    "n": 11
   },
   "+1": {
    "s_mps": -1.358,
    "n": 1
   },
   "+2": {
    "s_mps": -0.636,
    "n": 5
   },
   "+3": {
    "s_mps": -0.652,
    "n": 3
   },
   "+4": {
    "s_mps": -0.782,
    "n": 2
   },
   "+5": {
    "s_mps": -0.634,
    "n": 5
   },
   "+6": {
    "s_mps": -1.123,
    "n": 4
   }
  },
  "kew": {
   "-4": {
    "s_mps": 0.569,
    "n": 3
   },
   "-2": {
    "s_mps": 0.715,
    "n": 5
   },
   "-1": {
    "s_mps": -0.418,
    "n": 4
   },
   "+0": {
    "s_mps": 0.025,
    "n": 4
   },
   "+1": {
    "s_mps": -0.92,
    "n": 1
   },
   "+2": {
    "s_mps": -0.875,
    "n": 2
   },
   "+3": {
    "s_mps": -0.783,
    "n": 2
   },
   "+4": {
    "s_mps": -0.507,
    "n": 2
   },
   "+5": {
    "s_mps": -0.684,
    "n": 6
   },
   "+6": {
    "s_mps": -0.707,
    "n": 2
   }
  },
  "mortlake": {
   "-4": {
    "s_mps": 0.831,
    "n": 2
   },
   "-2": {
    "s_mps": 0.824,
    "n": 7
   },
   "-1": {
    "s_mps": -0.379,
    "n": 4
   },
   "+0": {
    "s_mps": -0.452,
    "n": 7
   },
   "+1": {
    "s_mps": -0.934,
    "n": 1
   },
   "+2": {
    "s_mps": -0.95,
    "n": 3
   },
   "+3": {
    "s_mps": -0.705,
    "n": 3
   },
   "+4": {
    "s_mps": -1.271,
    "n": 2
   },
   "+5": {
    "s_mps": -0.666,
    "n": 5
   },
   "+6": {
    "s_mps": -0.84,
    "n": 2
   }
  },
  "putney": {
   "-6": {
    "s_mps": -1.041,
    "n": 1
   },
   "-4": {
    "s_mps": 0.724,
    "n": 2
   },
   "-3": {
    "s_mps": -0.139,
    "n": 1
   },
   "-2": {
    "s_mps": 0.377,
    "n": 4
   },
   "-1": {
    "s_mps": -0.175,
    "n": 8
   },
   "+0": {
    "s_mps": -0.609,
    "n": 15
   },
   "+1": {
    "s_mps": -1.321,
    "n": 7
   },
   "+2": {
    "s_mps": -1.193,
    "n": 6
   },
   "+3": {
    "s_mps": -0.963,
    "n": 4
   },
   "+4": {
    "s_mps": -1.057,
    "n": 3
   },
   "+5": {
    "s_mps": -1.008,
    "n": 4
   },
   "+6": {
    "s_mps": -0.895,
    "n": 6
   }
  },
  "st_pauls": {
   "-4": {
    "s_mps": 0.824,
    "n": 2
   },
   "-3": {
    "s_mps": 0.111,
    "n": 1
   },
   "-2": {
    "s_mps": 0.83,
    "n": 4
   },
   "-1": {
    "s_mps": 0.138,
    "n": 8
   },
   "+0": {
    "s_mps": -0.353,
    "n": 13
   },
   "+1": {
    "s_mps": -1.042,
    "n": 5
   },
   "+2": {
    "s_mps": -0.797,
    "n": 6
   },
   "+3": {
    "s_mps": -0.653,
    "n": 4
   },
   "+4": {
    "s_mps": -1.476,
    "n": 2
   },
   "+5": {
    "s_mps": -0.736,
    "n": 4
   },
   "+6": {
    "s_mps": -0.661,
    "n": 7
   }
  },
  "syon": {
   "-2": {
    "s_mps": 0.925,
    "n": 1
   },
   "-1": {
    "s_mps": -0.046,
    "n": 2
   },
   "+0": {
    "s_mps": -0.114,
    "n": 1
   }
  }
 },
 "sessions_V_mps": {
  "18235690543": 3.952,
  "18235695968": 3.469,
  "18235701285": 3.011,
  "18434820504": 4.322,
  "18434841779": 4.01,
  "18434863455": 4.092,
  "18434892585": 4.198,
  "18434922285": 3.909,
  "18434955154": 3.975,
  "18435001755": 4.646,
  "18472190673": 4.278,
  "18472197148": 3.819,
  "18472205169": 4.447,
  "18538478807": 4.53,
  "18538488420": 3.831,
  "18538501562": 4.156,
  "18538516634": 3.854,
  "18538532690": 4.349,
  "18591505752": 3.88,
  "18623474893": 3.443,
  "18735791858": 3.983,
  "18735801488": 4.213,
  "18954854863": 4.887,
  "18954883163": 4.206,
  "18954905220": 4.176,
  "18954971120": 4.415,
  "18974862418": 4.143,
  "19359659676": 3.588,
  "19384799199": 3.388
 },
 "iterations": 31,
 "rmse_mps": 0.379,
 "sign_convention": "positive = stream pushing UPSTREAM (flood)"
}